insided/__init__.py
insided/api.py
insided/api_helper.py
insided/authorization.py
insided/gamification.py
insided/users.py
insided/webhooks.py
insided-1.0.1.dist-info/METADATA
insided-1.0.1.dist-info/WHEEL
insided-1.0.1.dist-info/top_level.txt
insided-1.0.1.dist-info/RECORD
