Metadata-Version: 2.1
Name: insided
Version: 1.0.1
Summary: Connect Python applications with the InSided API
Home-page: https://github.com/remstone7/insided-python
Author: Remington Stone
Author-email: remstone7@gmail.com
License: MIT
Keywords: insided,api
Platform: UNKNOWN
Classifier: Programming Language :: Python :: 3
Classifier: License :: OSI Approved :: MIT License
Requires-Dist: requests (>=2.24.0)
